AUTHORS.txt
CHANGES.txt
LICENSE.txt
MANIFEST.in
README.rst
setup.py
django_twitter.egg-info/PKG-INFO
django_twitter.egg-info/SOURCES.txt
django_twitter.egg-info/dependency_links.txt
django_twitter.egg-info/not-zip-safe
django_twitter.egg-info/requires.txt
django_twitter.egg-info/top_level.txt
twitter/__init__.py
twitter/admin.py
twitter/models.py
twitter/settings.py
twitter/signals.py
twitter/toauth.py
twitter/urls.py
twitter/views.py