Metadata-Version: 1.0
Name: django-twitter
Version: 0.1.0
Summary: An inobstrusive way to login with Twitter into your Django application.
Home-page: http://github.com/ahmontero/django-twitter
Author: Antonio Hinojo
Author-email: hello@ahmontero.com
License: Copyright (c) 2013 Antonio Hinojo.
